examples/__init__.py
examples/example_ControlLaw.py
examples/example_Parametric.py
examples/parameters_Rastriguin.py
examples/parameters_Rastriguin_DSM.py
examples/parameters_Rastriguin_Scipy.py
examples/parameters_control_law.py
examples/parameters_control_law_Lorentz.py
hygo/HYGO.py
hygo/__init__.py
hygo/individual.py
hygo/population.py
hygo/table.py
hygo/tools/CMA_ES.py
hygo/tools/DummyParams.py
hygo/tools/Parameter_help.txt
hygo/tools/__init__.py
hygo/tools/api_scipy.py
hygo/tools/choose_operation.py
hygo/tools/chromosome_to_params.py
hygo/tools/findKClosest.py
hygo/tools/individual_forced_generator.py
hygo/tools/operations.py
hygo/tools/params_to_chromosome.py
hygo/tools/parse_parameter_help.py
hygo/tools/round_params.py
hygo/tools/select_individual.py
hygo/tools/simplex.py
hygo-0.9.13.dist-info/licenses/LICENSE
hygo-0.9.13.dist-info/METADATA
hygo-0.9.13.dist-info/WHEEL
hygo-0.9.13.dist-info/top_level.txt
hygo-0.9.13.dist-info/RECORD
