Metadata-Version: 2.4
Name: HYGO
Version: 0.9.13
Summary: HYbrid Genetic Optimizer mixing parametric genetic optimization with genetic programming
Home-page: https://github.com/ipatazas/HYGO
Author: Isaac Robledo Martín
Author-email: Isaac Robledo Martin <isaac.robledo.martin@gmail.com>
License: MIT
Project-URL: Homepage, https://github.com/ipatazas/HYGO
Classifier: Programming Language :: Python :: 3
Classifier: License :: OSI Approved :: MIT License
Classifier: Operating System :: OS Independent
Requires-Python: >=3.7
License-File: LICENSE
Requires-Dist: numpy<2.0,>=1.16
Requires-Dist: scipy>=1.15,>=1.3
Requires-Dist: matplotlib>=3.0
Requires-Dist: pandas>=0.25
Requires-Dist: dill>=0.3.0
Dynamic: author
Dynamic: home-page
Dynamic: license-file
Dynamic: requires-python
